{
  "book": "the-private-papers-of-henry-ryecroft",
  "title": "The Private Papers of Henry Ryecroft",
  "description": "The Private Papers of Henry Ryecroft — knowledge fragments for AI agents",
  "language": "en",
  "generated": "2026-07-21",
  "version": 1,
  "meme_count": 126,
  "memes": [
    {
      "id": "About",
      "type": "overview",
      "label": "About This Wiki",
      "description": "A knowledge wiki for \"The Private Papers of Henry Ryecroft\" — this page is auto-generated from book metadata",
      "aliases": [
        "About",
        "关于"
      ],
      "tags": [],
      "quality": "unknown",
      "source_ref": "the-private-papers-of-henry-ryecroft:About",
      "relations": []
    },
    {
      "id": "Preface",
      "type": "chapter",
      "label": "Preface",
      "description": "Preface — Front Matter",
      "aliases": [
        "Preface"
      ],
      "tags": [],
      "quality": "unknown",
      "source_ref": "the-private-papers-of-henry-ryecroft:Preface",
      "relations": []
    },
    {
      "id": "autumn-i",
      "type": "chapter",
      "label": "Part III: Autumn — I",
      "description": "I — Part III: Autumn",
      "aliases": [
        "I"
      ],
      "tags": [],
      "quality": "unknown",
      "source_ref": "the-private-papers-of-henry-ryecroft:autumn-i",
      "relations": []
    },
    {
      "id": "autumn-ii",
      "type": "chapter",
      "label": "Part III: Autumn — II",
      "description": "II — Part III: Autumn",
      "aliases": [
        "II"
      ],
      "tags": [],
      "quality": "unknown",
      "source_ref": "the-private-papers-of-henry-ryecroft:autumn-ii",
      "relations": []
    },
    {
      "id": "autumn-iii",
      "type": "chapter",
      "label": "Part III: Autumn — III",
      "description": "III — Part III: Autumn",
      "aliases": [
        "III"
      ],
      "tags": [],
      "quality": "unknown",
      "source_ref": "the-private-papers-of-henry-ryecroft:autumn-iii",
      "relations": []
    },
    {
      "id": "autumn-iv",
      "type": "chapter",
      "label": "Part III: Autumn — IV",
      "description": "IV — Part III: Autumn",
      "aliases": [
        "IV"
      ],
      "tags": [],
      "quality": "unknown",
      "source_ref": "the-private-papers-of-henry-ryecroft:autumn-iv",
      "relations": []
    },
    {
      "id": "autumn-ix",
      "type": "chapter",
      "label": "Part III: Autumn — IX",
      "description": "IX — Part III: Autumn",
      "aliases": [
        "IX"
      ],
      "tags": [],
      "quality": "unknown",
      "source_ref": "the-private-papers-of-henry-ryecroft:autumn-ix",
      "relations": []
    },
    {
      "id": "autumn-v",
      "type": "chapter",
      "label": "Part III: Autumn — V",
      "description": "V — Part III: Autumn",
      "aliases": [
        "V"
      ],
      "tags": [],
      "quality": "unknown",
      "source_ref": "the-private-papers-of-henry-ryecroft:autumn-v",
      "relations": []
    },
    {
      "id": "autumn-vi",
      "type": "chapter",
      "label": "Part III: Autumn — VI",
      "description": "VI — Part III: Autumn",
      "aliases": [
        "VI"
      ],
      "tags": [],
      "quality": "unknown",
      "source_ref": "the-private-papers-of-henry-ryecroft:autumn-vi",
      "relations": []
    },
    {
      "id": "autumn-vii",
      "type": "chapter",
      "label": "Part III: Autumn — VII",
      "description": "VII — Part III: Autumn",
      "aliases": [
        "VII"
      ],
      "tags": [],
      "quality": "unknown",
      "source_ref": "the-private-papers-of-henry-ryecroft:autumn-vii",
      "relations": []
    },
    {
      "id": "autumn-viii",
      "type": "chapter",
      "label": "Part III: Autumn — VIII",
      "description": "VIII — Part III: Autumn",
      "aliases": [
        "VIII"
      ],
      "tags": [],
      "quality": "unknown",
      "source_ref": "the-private-papers-of-henry-ryecroft:autumn-viii",
      "relations": []
    },
    {
      "id": "autumn-x",
      "type": "chapter",
      "label": "Part III: Autumn — X",
      "description": "X — Part III: Autumn",
      "aliases": [
        "X"
      ],
      "tags": [],
      "quality": "unknown",
      "source_ref": "the-private-papers-of-henry-ryecroft:autumn-x",
      "relations": []
    },
    {
      "id": "autumn-xi",
      "type": "chapter",
      "label": "Part III: Autumn — XI",
      "description": "XI — Part III: Autumn",
      "aliases": [
        "XI"
      ],
      "tags": [],
      "quality": "unknown",
      "source_ref": "the-private-papers-of-henry-ryecroft:autumn-xi",
      "relations": []
    },
    {
      "id": "autumn-xii",
      "type": "chapter",
      "label": "Part III: Autumn — XII",
      "description": "XII — Part III: Autumn",
      "aliases": [
        "XII"
      ],
      "tags": [],
      "quality": "unknown",
      "source_ref": "the-private-papers-of-henry-ryecroft:autumn-xii",
      "relations": []
    },
    {
      "id": "autumn-xiii",
      "type": "chapter",
      "label": "Part III: Autumn — XIII",
      "description": "XIII — Part III: Autumn",
      "aliases": [
        "XIII"
      ],
      "tags": [],
      "quality": "unknown",
      "source_ref": "the-private-papers-of-henry-ryecroft:autumn-xiii",
      "relations": []
    },
    {
      "id": "autumn-xiv",
      "type": "chapter",
      "label": "Part III: Autumn — XIV",
      "description": "XIV — Part III: Autumn",
      "aliases": [
        "XIV"
      ],
      "tags": [],
      "quality": "unknown",
      "source_ref": "the-private-papers-of-henry-ryecroft:autumn-xiv",
      "relations": []
    },
    {
      "id": "autumn-xix",
      "type": "chapter",
      "label": "Part III: Autumn — XIX",
      "description": "XIX — Part III: Autumn",
      "aliases": [
        "XIX"
      ],
      "tags": [],
      "quality": "unknown",
      "source_ref": "the-private-papers-of-henry-ryecroft:autumn-xix",
      "relations": []
    },
    {
      "id": "autumn-xv",
      "type": "chapter",
      "label": "Part III: Autumn — XV",
      "description": "XV — Part III: Autumn",
      "aliases": [
        "XV"
      ],
      "tags": [],
      "quality": "unknown",
      "source_ref": "the-private-papers-of-henry-ryecroft:autumn-xv",
      "relations": []
    },
    {
      "id": "autumn-xvi",
      "type": "chapter",
      "label": "Part III: Autumn — XVI",
      "description": "XVI — Part III: Autumn",
      "aliases": [
        "XVI"
      ],
      "tags": [],
      "quality": "unknown",
      "source_ref": "the-private-papers-of-henry-ryecroft:autumn-xvi",
      "relations": []
    },
    {
      "id": "autumn-xvii",
      "type": "chapter",
      "label": "Part III: Autumn — XVII",
      "description": "XVII — Part III: Autumn",
      "aliases": [
        "XVII"
      ],
      "tags": [],
      "quality": "unknown",
      "source_ref": "the-private-papers-of-henry-ryecroft:autumn-xvii",
      "relations": []
    },
    {
      "id": "autumn-xviii",
      "type": "chapter",
      "label": "Part III: Autumn — XVIII",
      "description": "XVIII — Part III: Autumn",
      "aliases": [
        "XVIII"
      ],
      "tags": [],
      "quality": "unknown",
      "source_ref": "the-private-papers-of-henry-ryecroft:autumn-xviii",
      "relations": []
    },
    {
      "id": "autumn-xx",
      "type": "chapter",
      "label": "Part III: Autumn — XX",
      "description": "XX — Part III: Autumn",
      "aliases": [
        "XX"
      ],
      "tags": [],
      "quality": "unknown",
      "source_ref": "the-private-papers-of-henry-ryecroft:autumn-xx",
      "relations": []
    },
    {
      "id": "autumn-xxi",
      "type": "chapter",
      "label": "Part III: Autumn — XXI",
      "description": "XXI — Part III: Autumn",
      "aliases": [
        "XXI"
      ],
      "tags": [],
      "quality": "unknown",
      "source_ref": "the-private-papers-of-henry-ryecroft:autumn-xxi",
      "relations": []
    },
    {
      "id": "autumn-xxii",
      "type": "chapter",
      "label": "Part III: Autumn — XXII",
      "description": "XXII — Part III: Autumn",
      "aliases": [
        "XXII"
      ],
      "tags": [],
      "quality": "unknown",
      "source_ref": "the-private-papers-of-henry-ryecroft:autumn-xxii",
      "relations": []
    },
    {
      "id": "autumn-xxiii",
      "type": "chapter",
      "label": "Part III: Autumn — XXIII",
      "description": "XXIII — Part III: Autumn",
      "aliases": [
        "XXIII"
      ],
      "tags": [],
      "quality": "unknown",
      "source_ref": "the-private-papers-of-henry-ryecroft:autumn-xxiii",
      "relations": []
    },
    {
      "id": "autumn-xxiv",
      "type": "chapter",
      "label": "Part III: Autumn — XXIV",
      "description": "XXIV — Part III: Autumn",
      "aliases": [
        "XXIV"
      ],
      "tags": [],
      "quality": "unknown",
      "source_ref": "the-private-papers-of-henry-ryecroft:autumn-xxiv",
      "relations": []
    },
    {
      "id": "autumn-xxv",
      "type": "chapter",
      "label": "Part III: Autumn — XXV",
      "description": "XXV — Part III: Autumn",
      "aliases": [
        "XXV"
      ],
      "tags": [],
      "quality": "unknown",
      "source_ref": "the-private-papers-of-henry-ryecroft:autumn-xxv",
      "relations": []
    },
    {
      "id": "british-museum-reading-room",
      "type": "organization",
      "label": "The British Museum Reading Room",
      "description": "The great domed reading room of the British Museum, where Henry Ryecroft pursued classical scholarship during his years of poverty in London, finding intellectual sustenance amid physical deprivation.",
      "aliases": [
        "the Reading-Room",
        "the British Museum",
        "the great Reading-Room"
      ],
      "tags": [],
      "quality": "featured",
      "source_ref": "the-private-papers-of-henry-ryecroft:british-museum-reading-room",
      "relations": [
        {
          "type": "related",
          "target": "william-shakespeare",
          "label": "william-shakespeare"
        },
        {
          "type": "related",
          "target": "literature-and-the-classics",
          "label": "literature-and-the-classics"
        },
        {
          "type": "related",
          "target": "london",
          "label": "london"
        },
        {
          "type": "related",
          "target": "tottenham-court-road",
          "label": "tottenham-court-road"
        },
        {
          "type": "related",
          "target": "henry-ryecroft",
          "label": "henry-ryecroft"
        }
      ]
    },
    {
      "id": "cottage-near-exeter",
      "type": "place",
      "label": "cottage-near-exeter",
      "description": "",
      "aliases": [
        "Ryecroft's cottage",
        "cottage in Devon"
      ],
      "tags": [
        "Devon",
        "retirement",
        "countryside",
        "home"
      ],
      "quality": "basic",
      "source_ref": "the-private-papers-of-henry-ryecroft:cottage-near-exeter",
      "relations": []
    },
    {
      "id": "devon",
      "type": "place",
      "label": "Devon",
      "description": "The rural county in southwest England where Henry Ryecroft found his final home and the setting of his tranquil retirement after decades of poverty in London.",
      "aliases": [
        "Devonshire"
      ],
      "tags": [],
      "quality": "featured",
      "source_ref": "the-private-papers-of-henry-ryecroft:devon",
      "relations": [
        {
          "type": "related",
          "target": "cottage-near-exeter",
          "label": "cottage-near-exeter"
        },
        {
          "type": "related",
          "target": "london",
          "label": "london"
        },
        {
          "type": "related",
          "target": "tottenham-court-road",
          "label": "tottenham-court-road"
        },
        {
          "type": "related",
          "target": "henry-ryecroft",
          "label": "henry-ryecroft"
        },
        {
          "type": "related",
          "target": "the-seasons-in-ryecroft",
          "label": "the-seasons-in-ryecroft"
        }
      ]
    },
    {
      "id": "george-gissing",
      "type": "person",
      "label": "george-gissing",
      "description": "",
      "aliases": [
        "Gissing",
        "G. G."
      ],
      "tags": [
        "author",
        "novelist",
        "Victorian",
        "editor"
      ],
      "quality": "basic",
      "source_ref": "the-private-papers-of-henry-ryecroft:george-gissing",
      "relations": []
    },
    {
      "id": "henry-ryecroft",
      "type": "person",
      "label": "henry-ryecroft",
      "description": "",
      "aliases": [
        "Ryecroft"
      ],
      "tags": [
        "protagonist",
        "writer",
        "memoirist",
        "London",
        "Devon"
      ],
      "quality": "basic",
      "source_ref": "the-private-papers-of-henry-ryecroft:henry-ryecroft",
      "relations": [
        {
          "type": "related",
          "target": "cottage-near-exeter",
          "label": "cottage-near-exeter"
        }
      ]
    },
    {
      "id": "johann-wolfgang-von-goethe",
      "type": "person",
      "label": "Johann Wolfgang von Goethe",
      "description": "German poet, dramatist, and polymath (1749–1832), cited by Henry Ryecroft as exemplar of the born artist whose creative spontaneity transcends method.",
      "aliases": [
        "Goethe"
      ],
      "tags": [],
      "quality": "featured",
      "source_ref": "the-private-papers-of-henry-ryecroft:johann-wolfgang-von-goethe",
      "relations": [
        {
          "type": "related",
          "target": "william-shakespeare",
          "label": "william-shakespeare"
        },
        {
          "type": "related",
          "target": "literature-and-the-classics",
          "label": "literature-and-the-classics"
        },
        {
          "type": "related",
          "target": "henry-ryecroft",
          "label": "henry-ryecroft"
        },
        {
          "type": "related",
          "target": "british-museum-reading-room",
          "label": "british-museum-reading-room"
        }
      ]
    },
    {
      "id": "literary-london",
      "type": "organization",
      "label": "literary-london",
      "description": "",
      "aliases": [
        "the London literary world",
        "literary marketplace"
      ],
      "tags": [
        "London",
        "literary-marketplace",
        "Victorian",
        "publishing",
        "writers"
      ],
      "quality": "basic",
      "source_ref": "the-private-papers-of-henry-ryecroft:literary-london",
      "relations": [
        {
          "type": "related",
          "target": "the-periodical-press",
          "label": "the-periodical-press"
        },
        {
          "type": "related",
          "target": "poverty-and-literary-life",
          "label": "poverty-and-literary-life"
        }
      ]
    },
    {
      "id": "literature-and-the-classics",
      "type": "concept",
      "label": "Literature and the Classics",
      "description": "Henry Ryecroft's lifelong devotion to classical and European literature, which sustained him through poverty and enriched his years of retirement in Devon.",
      "aliases": [],
      "tags": [],
      "quality": "featured",
      "source_ref": "the-private-papers-of-henry-ryecroft:literature-and-the-classics",
      "relations": [
        {
          "type": "related",
          "target": "william-shakespeare",
          "label": "william-shakespeare"
        },
        {
          "type": "related",
          "target": "johann-wolfgang-von-goethe",
          "label": "johann-wolfgang-von-goethe"
        },
        {
          "type": "related",
          "target": "british-museum-reading-room",
          "label": "british-museum-reading-room"
        },
        {
          "type": "related",
          "target": "henry-ryecroft",
          "label": "henry-ryecroft"
        },
        {
          "type": "related",
          "target": "the-seasons-in-ryecroft",
          "label": "the-seasons-in-ryecroft"
        }
      ]
    },
    {
      "id": "london",
      "type": "place",
      "label": "london",
      "description": "",
      "aliases": [
        "London suburb"
      ],
      "tags": [
        "city",
        "urban",
        "poverty",
        "literary-life"
      ],
      "quality": "basic",
      "source_ref": "the-private-papers-of-henry-ryecroft:london",
      "relations": [
        {
          "type": "related",
          "target": "cottage-near-exeter",
          "label": "cottage-near-exeter"
        },
        {
          "type": "related",
          "target": "poverty-and-literary-life",
          "label": "poverty-and-literary-life"
        }
      ]
    },
    {
      "id": "poverty-and-literary-life",
      "type": "concept",
      "label": "poverty-and-literary-life",
      "description": "",
      "aliases": [
        "literary poverty",
        "hackwork",
        "Grub Street life"
      ],
      "tags": [
        "poverty",
        "writing",
        "hackwork",
        "London",
        "Grub-Street"
      ],
      "quality": "basic",
      "source_ref": "the-private-papers-of-henry-ryecroft:poverty-and-literary-life",
      "relations": [
        {
          "type": "related",
          "target": "retirement-and-leisure",
          "label": "retirement-and-leisure"
        }
      ]
    },
    {
      "id": "retirement-and-leisure",
      "type": "concept",
      "label": "retirement-and-leisure",
      "description": "",
      "aliases": [
        "leisure",
        "retirement",
        "freedom from toil"
      ],
      "tags": [
        "retirement",
        "leisure",
        "freedom",
        "contentment",
        "work"
      ],
      "quality": "basic",
      "source_ref": "the-private-papers-of-henry-ryecroft:retirement-and-leisure",
      "relations": [
        {
          "type": "related",
          "target": "poverty-and-literary-life",
          "label": "poverty-and-literary-life"
        },
        {
          "type": "related",
          "target": "cottage-near-exeter",
          "label": "cottage-near-exeter"
        }
      ]
    },
    {
      "id": "ryecrofts-death",
      "type": "event",
      "label": "ryecrofts-death",
      "description": "",
      "aliases": [
        "death of Ryecroft"
      ],
      "tags": [
        "death",
        "heart-disease",
        "summer",
        "Devon"
      ],
      "quality": "basic",
      "source_ref": "the-private-papers-of-henry-ryecroft:ryecrofts-death",
      "relations": [
        {
          "type": "related",
          "target": "the-bequest",
          "label": "the-bequest"
        },
        {
          "type": "related",
          "target": "cottage-near-exeter",
          "label": "cottage-near-exeter"
        }
      ]
    },
    {
      "id": "ryecrofts-first-visit-to-devon",
      "type": "event",
      "label": "Ryecroft's First Visit to Devon",
      "description": "The transformative journey to Devon that awakened Henry Ryecroft's dormant sensibilities and prefigured his permanent retreat from London literary life.",
      "aliases": [],
      "tags": [],
      "quality": "featured",
      "source_ref": "the-private-papers-of-henry-ryecroft:ryecrofts-first-visit-to-devon",
      "relations": [
        {
          "type": "related",
          "target": "devon",
          "label": "devon"
        },
        {
          "type": "related",
          "target": "cottage-near-exeter",
          "label": "cottage-near-exeter"
        },
        {
          "type": "related",
          "target": "london",
          "label": "london"
        },
        {
          "type": "related",
          "target": "henry-ryecroft",
          "label": "henry-ryecroft"
        },
        {
          "type": "related",
          "target": "the-bequest",
          "label": "the-bequest"
        }
      ]
    },
    {
      "id": "spring-i",
      "type": "chapter",
      "label": "Part I: Spring — I",
      "description": "I — Part I: Spring",
      "aliases": [
        "I"
      ],
      "tags": [],
      "quality": "unknown",
      "source_ref": "the-private-papers-of-henry-ryecroft:spring-i",
      "relations": []
    },
    {
      "id": "spring-ii",
      "type": "chapter",
      "label": "Part I: Spring — II",
      "description": "II — Part I: Spring",
      "aliases": [
        "II"
      ],
      "tags": [],
      "quality": "unknown",
      "source_ref": "the-private-papers-of-henry-ryecroft:spring-ii",
      "relations": []
    },
    {
      "id": "spring-iii",
      "type": "chapter",
      "label": "Part I: Spring — III",
      "description": "III — Part I: Spring",
      "aliases": [
        "III"
      ],
      "tags": [],
      "quality": "unknown",
      "source_ref": "the-private-papers-of-henry-ryecroft:spring-iii",
      "relations": []
    },
    {
      "id": "spring-iv",
      "type": "chapter",
      "label": "Part I: Spring — IV",
      "description": "IV — Part I: Spring",
      "aliases": [
        "IV"
      ],
      "tags": [],
      "quality": "unknown",
      "source_ref": "the-private-papers-of-henry-ryecroft:spring-iv",
      "relations": []
    },
    {
      "id": "spring-ix",
      "type": "chapter",
      "label": "Part I: Spring — IX",
      "description": "IX — Part I: Spring",
      "aliases": [
        "IX"
      ],
      "tags": [],
      "quality": "unknown",
      "source_ref": "the-private-papers-of-henry-ryecroft:spring-ix",
      "relations": []
    },
    {
      "id": "spring-v",
      "type": "chapter",
      "label": "Part I: Spring — V",
      "description": "V — Part I: Spring",
      "aliases": [
        "V"
      ],
      "tags": [],
      "quality": "unknown",
      "source_ref": "the-private-papers-of-henry-ryecroft:spring-v",
      "relations": []
    },
    {
      "id": "spring-vi",
      "type": "chapter",
      "label": "Part I: Spring — VI",
      "description": "VI — Part I: Spring",
      "aliases": [
        "VI"
      ],
      "tags": [],
      "quality": "unknown",
      "source_ref": "the-private-papers-of-henry-ryecroft:spring-vi",
      "relations": []
    },
    {
      "id": "spring-vii",
      "type": "chapter",
      "label": "Part I: Spring — VII",
      "description": "VII — Part I: Spring",
      "aliases": [
        "VII"
      ],
      "tags": [],
      "quality": "unknown",
      "source_ref": "the-private-papers-of-henry-ryecroft:spring-vii",
      "relations": []
    },
    {
      "id": "spring-viii",
      "type": "chapter",
      "label": "Part I: Spring — VIII",
      "description": "VIII — Part I: Spring",
      "aliases": [
        "VIII"
      ],
      "tags": [],
      "quality": "unknown",
      "source_ref": "the-private-papers-of-henry-ryecroft:spring-viii",
      "relations": []
    },
    {
      "id": "spring-x",
      "type": "chapter",
      "label": "Part I: Spring — X",
      "description": "X — Part I: Spring",
      "aliases": [
        "X"
      ],
      "tags": [],
      "quality": "unknown",
      "source_ref": "the-private-papers-of-henry-ryecroft:spring-x",
      "relations": []
    },
    {
      "id": "spring-xi",
      "type": "chapter",
      "label": "Part I: Spring — XI",
      "description": "XI — Part I: Spring",
      "aliases": [
        "XI"
      ],
      "tags": [],
      "quality": "unknown",
      "source_ref": "the-private-papers-of-henry-ryecroft:spring-xi",
      "relations": []
    },
    {
      "id": "spring-xii",
      "type": "chapter",
      "label": "Part I: Spring — XII",
      "description": "XII — Part I: Spring",
      "aliases": [
        "XII"
      ],
      "tags": [],
      "quality": "unknown",
      "source_ref": "the-private-papers-of-henry-ryecroft:spring-xii",
      "relations": []
    },
    {
      "id": "spring-xiii",
      "type": "chapter",
      "label": "Part I: Spring — XIII",
      "description": "XIII — Part I: Spring",
      "aliases": [
        "XIII"
      ],
      "tags": [],
      "quality": "unknown",
      "source_ref": "the-private-papers-of-henry-ryecroft:spring-xiii",
      "relations": []
    },
    {
      "id": "spring-xiv",
      "type": "chapter",
      "label": "Part I: Spring — XIV",
      "description": "XIV — Part I: Spring",
      "aliases": [
        "XIV"
      ],
      "tags": [],
      "quality": "unknown",
      "source_ref": "the-private-papers-of-henry-ryecroft:spring-xiv",
      "relations": []
    },
    {
      "id": "spring-xix",
      "type": "chapter",
      "label": "Part I: Spring — XIX",
      "description": "XIX — Part I: Spring",
      "aliases": [
        "XIX"
      ],
      "tags": [],
      "quality": "unknown",
      "source_ref": "the-private-papers-of-henry-ryecroft:spring-xix",
      "relations": []
    },
    {
      "id": "spring-xv",
      "type": "chapter",
      "label": "Part I: Spring — XV",
      "description": "XV — Part I: Spring",
      "aliases": [
        "XV"
      ],
      "tags": [],
      "quality": "unknown",
      "source_ref": "the-private-papers-of-henry-ryecroft:spring-xv",
      "relations": []
    },
    {
      "id": "spring-xvi",
      "type": "chapter",
      "label": "Part I: Spring — XVI",
      "description": "XVI — Part I: Spring",
      "aliases": [
        "XVI"
      ],
      "tags": [],
      "quality": "unknown",
      "source_ref": "the-private-papers-of-henry-ryecroft:spring-xvi",
      "relations": []
    },
    {
      "id": "spring-xvii",
      "type": "chapter",
      "label": "Part I: Spring — XVII",
      "description": "XVII — Part I: Spring",
      "aliases": [
        "XVII"
      ],
      "tags": [],
      "quality": "unknown",
      "source_ref": "the-private-papers-of-henry-ryecroft:spring-xvii",
      "relations": []
    },
    {
      "id": "spring-xviii",
      "type": "chapter",
      "label": "Part I: Spring — XVIII",
      "description": "XVIII — Part I: Spring",
      "aliases": [
        "XVIII"
      ],
      "tags": [],
      "quality": "unknown",
      "source_ref": "the-private-papers-of-henry-ryecroft:spring-xviii",
      "relations": []
    },
    {
      "id": "spring-xx",
      "type": "chapter",
      "label": "Part I: Spring — XX",
      "description": "XX — Part I: Spring",
      "aliases": [
        "XX"
      ],
      "tags": [],
      "quality": "unknown",
      "source_ref": "the-private-papers-of-henry-ryecroft:spring-xx",
      "relations": []
    },
    {
      "id": "spring-xxi",
      "type": "chapter",
      "label": "Part I: Spring — XXI",
      "description": "XXI — Part I: Spring",
      "aliases": [
        "XXI"
      ],
      "tags": [],
      "quality": "unknown",
      "source_ref": "the-private-papers-of-henry-ryecroft:spring-xxi",
      "relations": []
    },
    {
      "id": "spring-xxii",
      "type": "chapter",
      "label": "Part I: Spring — XXII",
      "description": "XXII — Part I: Spring",
      "aliases": [
        "XXII"
      ],
      "tags": [],
      "quality": "unknown",
      "source_ref": "the-private-papers-of-henry-ryecroft:spring-xxii",
      "relations": []
    },
    {
      "id": "spring-xxiii",
      "type": "chapter",
      "label": "Part I: Spring — XXIII",
      "description": "XXIII — Part I: Spring",
      "aliases": [
        "XXIII"
      ],
      "tags": [],
      "quality": "unknown",
      "source_ref": "the-private-papers-of-henry-ryecroft:spring-xxiii",
      "relations": []
    },
    {
      "id": "spring-xxiv",
      "type": "chapter",
      "label": "Part I: Spring — XXIV",
      "description": "XXIV — Part I: Spring",
      "aliases": [
        "XXIV"
      ],
      "tags": [],
      "quality": "unknown",
      "source_ref": "the-private-papers-of-henry-ryecroft:spring-xxiv",
      "relations": []
    },
    {
      "id": "spring-xxv",
      "type": "chapter",
      "label": "Part I: Spring — XXV",
      "description": "XXV — Part I: Spring",
      "aliases": [
        "XXV"
      ],
      "tags": [],
      "quality": "unknown",
      "source_ref": "the-private-papers-of-henry-ryecroft:spring-xxv",
      "relations": []
    },
    {
      "id": "summer-i",
      "type": "chapter",
      "label": "Part II: Summer — I",
      "description": "I — Part II: Summer",
      "aliases": [
        "I"
      ],
      "tags": [],
      "quality": "unknown",
      "source_ref": "the-private-papers-of-henry-ryecroft:summer-i",
      "relations": []
    },
    {
      "id": "summer-ii",
      "type": "chapter",
      "label": "Part II: Summer — II",
      "description": "II — Part II: Summer",
      "aliases": [
        "II"
      ],
      "tags": [],
      "quality": "unknown",
      "source_ref": "the-private-papers-of-henry-ryecroft:summer-ii",
      "relations": []
    },
    {
      "id": "summer-iii",
      "type": "chapter",
      "label": "Part II: Summer — III",
      "description": "III — Part II: Summer",
      "aliases": [
        "III"
      ],
      "tags": [],
      "quality": "unknown",
      "source_ref": "the-private-papers-of-henry-ryecroft:summer-iii",
      "relations": []
    },
    {
      "id": "summer-iv",
      "type": "chapter",
      "label": "Part II: Summer — IV",
      "description": "IV — Part II: Summer",
      "aliases": [
        "IV"
      ],
      "tags": [],
      "quality": "unknown",
      "source_ref": "the-private-papers-of-henry-ryecroft:summer-iv",
      "relations": []
    },
    {
      "id": "summer-ix",
      "type": "chapter",
      "label": "Part II: Summer — IX",
      "description": "IX — Part II: Summer",
      "aliases": [
        "IX"
      ],
      "tags": [],
      "quality": "unknown",
      "source_ref": "the-private-papers-of-henry-ryecroft:summer-ix",
      "relations": []
    },
    {
      "id": "summer-v",
      "type": "chapter",
      "label": "Part II: Summer — V",
      "description": "V — Part II: Summer",
      "aliases": [
        "V"
      ],
      "tags": [],
      "quality": "unknown",
      "source_ref": "the-private-papers-of-henry-ryecroft:summer-v",
      "relations": []
    },
    {
      "id": "summer-vi",
      "type": "chapter",
      "label": "Part II: Summer — VI",
      "description": "VI — Part II: Summer",
      "aliases": [
        "VI"
      ],
      "tags": [],
      "quality": "unknown",
      "source_ref": "the-private-papers-of-henry-ryecroft:summer-vi",
      "relations": []
    },
    {
      "id": "summer-vii",
      "type": "chapter",
      "label": "Part II: Summer — VII",
      "description": "VII — Part II: Summer",
      "aliases": [
        "VII"
      ],
      "tags": [],
      "quality": "unknown",
      "source_ref": "the-private-papers-of-henry-ryecroft:summer-vii",
      "relations": []
    },
    {
      "id": "summer-viii",
      "type": "chapter",
      "label": "Part II: Summer — VIII",
      "description": "VIII — Part II: Summer",
      "aliases": [
        "VIII"
      ],
      "tags": [],
      "quality": "unknown",
      "source_ref": "the-private-papers-of-henry-ryecroft:summer-viii",
      "relations": []
    },
    {
      "id": "summer-x",
      "type": "chapter",
      "label": "Part II: Summer — X",
      "description": "X — Part II: Summer",
      "aliases": [
        "X"
      ],
      "tags": [],
      "quality": "unknown",
      "source_ref": "the-private-papers-of-henry-ryecroft:summer-x",
      "relations": []
    },
    {
      "id": "summer-xi",
      "type": "chapter",
      "label": "Part II: Summer — XI",
      "description": "XI — Part II: Summer",
      "aliases": [
        "XI"
      ],
      "tags": [],
      "quality": "unknown",
      "source_ref": "the-private-papers-of-henry-ryecroft:summer-xi",
      "relations": []
    },
    {
      "id": "summer-xii",
      "type": "chapter",
      "label": "Part II: Summer — XII",
      "description": "XII — Part II: Summer",
      "aliases": [
        "XII"
      ],
      "tags": [],
      "quality": "unknown",
      "source_ref": "the-private-papers-of-henry-ryecroft:summer-xii",
      "relations": []
    },
    {
      "id": "summer-xiii",
      "type": "chapter",
      "label": "Part II: Summer — XIII",
      "description": "XIII — Part II: Summer",
      "aliases": [
        "XIII"
      ],
      "tags": [],
      "quality": "unknown",
      "source_ref": "the-private-papers-of-henry-ryecroft:summer-xiii",
      "relations": []
    },
    {
      "id": "summer-xiv",
      "type": "chapter",
      "label": "Part II: Summer — XIV",
      "description": "XIV — Part II: Summer",
      "aliases": [
        "XIV"
      ],
      "tags": [],
      "quality": "unknown",
      "source_ref": "the-private-papers-of-henry-ryecroft:summer-xiv",
      "relations": []
    },
    {
      "id": "summer-xix",
      "type": "chapter",
      "label": "Part II: Summer — XIX",
      "description": "XIX — Part II: Summer",
      "aliases": [
        "XIX"
      ],
      "tags": [],
      "quality": "unknown",
      "source_ref": "the-private-papers-of-henry-ryecroft:summer-xix",
      "relations": []
    },
    {
      "id": "summer-xv",
      "type": "chapter",
      "label": "Part II: Summer — XV",
      "description": "XV — Part II: Summer",
      "aliases": [
        "XV"
      ],
      "tags": [],
      "quality": "unknown",
      "source_ref": "the-private-papers-of-henry-ryecroft:summer-xv",
      "relations": []
    },
    {
      "id": "summer-xvi",
      "type": "chapter",
      "label": "Part II: Summer — XVI",
      "description": "XVI — Part II: Summer",
      "aliases": [
        "XVI"
      ],
      "tags": [],
      "quality": "unknown",
      "source_ref": "the-private-papers-of-henry-ryecroft:summer-xvi",
      "relations": []
    },
    {
      "id": "summer-xvii",
      "type": "chapter",
      "label": "Part II: Summer — XVII",
      "description": "XVII — Part II: Summer",
      "aliases": [
        "XVII"
      ],
      "tags": [],
      "quality": "unknown",
      "source_ref": "the-private-papers-of-henry-ryecroft:summer-xvii",
      "relations": []
    },
    {
      "id": "summer-xviii",
      "type": "chapter",
      "label": "Part II: Summer — XVIII",
      "description": "XVIII — Part II: Summer",
      "aliases": [
        "XVIII"
      ],
      "tags": [],
      "quality": "unknown",
      "source_ref": "the-private-papers-of-henry-ryecroft:summer-xviii",
      "relations": []
    },
    {
      "id": "summer-xx",
      "type": "chapter",
      "label": "Part II: Summer — XX",
      "description": "XX — Part II: Summer",
      "aliases": [
        "XX"
      ],
      "tags": [],
      "quality": "unknown",
      "source_ref": "the-private-papers-of-henry-ryecroft:summer-xx",
      "relations": []
    },
    {
      "id": "summer-xxi",
      "type": "chapter",
      "label": "Part II: Summer — XXI",
      "description": "XXI — Part II: Summer",
      "aliases": [
        "XXI"
      ],
      "tags": [],
      "quality": "unknown",
      "source_ref": "the-private-papers-of-henry-ryecroft:summer-xxi",
      "relations": []
    },
    {
      "id": "summer-xxii",
      "type": "chapter",
      "label": "Part II: Summer — XXII",
      "description": "XXII — Part II: Summer",
      "aliases": [
        "XXII"
      ],
      "tags": [],
      "quality": "unknown",
      "source_ref": "the-private-papers-of-henry-ryecroft:summer-xxii",
      "relations": []
    },
    {
      "id": "summer-xxiii",
      "type": "chapter",
      "label": "Part II: Summer — XXIII",
      "description": "XXIII — Part II: Summer",
      "aliases": [
        "XXIII"
      ],
      "tags": [],
      "quality": "unknown",
      "source_ref": "the-private-papers-of-henry-ryecroft:summer-xxiii",
      "relations": []
    },
    {
      "id": "summer-xxiv",
      "type": "chapter",
      "label": "Part II: Summer — XXIV",
      "description": "XXIV — Part II: Summer",
      "aliases": [
        "XXIV"
      ],
      "tags": [],
      "quality": "unknown",
      "source_ref": "the-private-papers-of-henry-ryecroft:summer-xxiv",
      "relations": []
    },
    {
      "id": "summer-xxv",
      "type": "chapter",
      "label": "Part II: Summer — XXV",
      "description": "XXV — Part II: Summer",
      "aliases": [
        "XXV"
      ],
      "tags": [],
      "quality": "unknown",
      "source_ref": "the-private-papers-of-henry-ryecroft:summer-xxv",
      "relations": []
    },
    {
      "id": "summer-xxvi",
      "type": "chapter",
      "label": "Part II: Summer — XXVI",
      "description": "XXVI — Part II: Summer",
      "aliases": [
        "XXVI"
      ],
      "tags": [],
      "quality": "unknown",
      "source_ref": "the-private-papers-of-henry-ryecroft:summer-xxvi",
      "relations": []
    },
    {
      "id": "summer-xxvii",
      "type": "chapter",
      "label": "Part II: Summer — XXVII",
      "description": "XXVII — Part II: Summer",
      "aliases": [
        "XXVII"
      ],
      "tags": [],
      "quality": "unknown",
      "source_ref": "the-private-papers-of-henry-ryecroft:summer-xxvii",
      "relations": []
    },
    {
      "id": "the-bequest",
      "type": "event",
      "label": "the-bequest",
      "description": "",
      "aliases": [
        "the annuity",
        "Ryecroft's legacy",
        "the three hundred pounds"
      ],
      "tags": [
        "annuity",
        "inheritance",
        "turning-point",
        "retirement"
      ],
      "quality": "basic",
      "source_ref": "the-private-papers-of-henry-ryecroft:the-bequest",
      "relations": [
        {
          "type": "related",
          "target": "retirement-and-leisure",
          "label": "retirement-and-leisure"
        },
        {
          "type": "related",
          "target": "cottage-near-exeter",
          "label": "cottage-near-exeter"
        }
      ]
    },
    {
      "id": "the-diamond-jubilee-1897",
      "type": "event",
      "label": "The Diamond Jubilee (1897)",
      "description": "Queen Victoria's Diamond Jubilee of 1897, observed by Henry Ryecroft with a characteristic mixture of sympathy for popular celebration and elegiac reflection on the passing of an age.",
      "aliases": [
        "the Jubilee",
        "the second Jubilee",
        "Queen Victoria's Diamond Jubilee"
      ],
      "tags": [],
      "quality": "featured",
      "source_ref": "the-private-papers-of-henry-ryecroft:the-diamond-jubilee-1897",
      "relations": [
        {
          "type": "related",
          "target": "london",
          "label": "london"
        },
        {
          "type": "related",
          "target": "henry-ryecroft",
          "label": "henry-ryecroft"
        },
        {
          "type": "related",
          "target": "literature-and-the-classics",
          "label": "literature-and-the-classics"
        },
        {
          "type": "related",
          "target": "tottenham-court-road",
          "label": "tottenham-court-road"
        }
      ]
    },
    {
      "id": "the-periodical-press",
      "type": "organization",
      "label": "the-periodical-press",
      "description": "",
      "aliases": [
        "the press",
        "literary journals",
        "Victorian periodicals"
      ],
      "tags": [
        "publishing",
        "periodicals",
        "journalism",
        "Victorian",
        "hackwork"
      ],
      "quality": "basic",
      "source_ref": "the-private-papers-of-henry-ryecroft:the-periodical-press",
      "relations": [
        {
          "type": "related",
          "target": "poverty-and-literary-life",
          "label": "poverty-and-literary-life"
        }
      ]
    },
    {
      "id": "the-seasons-in-ryecroft",
      "type": "concept",
      "label": "The Seasons in Ryecroft",
      "description": "The organizing principle of Henry Ryecroft's private papers, in which the cycle of spring, summer, autumn, and winter structures both the narrative and the author's philosophical reflections on nature, mortality, and contentment.",
      "aliases": [],
      "tags": [],
      "quality": "featured",
      "source_ref": "the-private-papers-of-henry-ryecroft:the-seasons-in-ryecroft",
      "relations": [
        {
          "type": "related",
          "target": "devon",
          "label": "devon"
        },
        {
          "type": "related",
          "target": "cottage-near-exeter",
          "label": "cottage-near-exeter"
        },
        {
          "type": "related",
          "target": "literature-and-the-classics",
          "label": "literature-and-the-classics"
        },
        {
          "type": "related",
          "target": "henry-ryecroft",
          "label": "henry-ryecroft"
        }
      ]
    },
    {
      "id": "the-secondhand-bookstalls-of-london",
      "type": "organization",
      "label": "The Secondhand Bookstalls of London",
      "description": "The secondhand bookshops and street stalls of Victorian London — particularly those in Holywell Street and Goodge Street — where Henry Ryecroft acquired his library through sacrifice and discovered the material culture of books.",
      "aliases": [
        "London bookstalls",
        "the Holywell Street bookshop",
        "the Goodge Street stall"
      ],
      "tags": [],
      "quality": "featured",
      "source_ref": "the-private-papers-of-henry-ryecroft:the-secondhand-bookstalls-of-london",
      "relations": [
        {
          "type": "related",
          "target": "literature-and-the-classics",
          "label": "literature-and-the-classics"
        },
        {
          "type": "related",
          "target": "british-museum-reading-room",
          "label": "british-museum-reading-room"
        },
        {
          "type": "related",
          "target": "london",
          "label": "london"
        },
        {
          "type": "related",
          "target": "tottenham-court-road",
          "label": "tottenham-court-road"
        },
        {
          "type": "related",
          "target": "william-shakespeare",
          "label": "william-shakespeare"
        }
      ]
    },
    {
      "id": "title-page-intro",
      "type": "chapter",
      "label": "The Private Papers of Henry Ryecroft",
      "description": "The Private Papers of Henry Ryecroft — Front Matter",
      "aliases": [
        "The Private Papers of Henry Ryecroft"
      ],
      "tags": [],
      "quality": "unknown",
      "source_ref": "the-private-papers-of-henry-ryecroft:title-page-intro",
      "relations": []
    },
    {
      "id": "tottenham-court-road",
      "type": "place",
      "label": "Tottenham Court Road",
      "description": "A London thoroughfare and the surrounding district where Henry Ryecroft lodged in desperate poverty during his early literary career, later recalled with unexpected affection.",
      "aliases": [
        "Tottenham Court Road district"
      ],
      "tags": [],
      "quality": "featured",
      "source_ref": "the-private-papers-of-henry-ryecroft:tottenham-court-road",
      "relations": [
        {
          "type": "related",
          "target": "london",
          "label": "london"
        },
        {
          "type": "related",
          "target": "devon",
          "label": "devon"
        },
        {
          "type": "related",
          "target": "cottage-near-exeter",
          "label": "cottage-near-exeter"
        },
        {
          "type": "related",
          "target": "henry-ryecroft",
          "label": "henry-ryecroft"
        },
        {
          "type": "related",
          "target": "british-museum-reading-room",
          "label": "british-museum-reading-room"
        }
      ]
    },
    {
      "id": "william-shakespeare",
      "type": "person",
      "label": "William Shakespeare",
      "description": "English playwright and poet (1564–1616), revered by Henry Ryecroft as the supreme literary master whose works served as lifelong companions through poverty and leisure alike.",
      "aliases": [
        "Shakespeare",
        "the Bard",
        "the great Enchanter"
      ],
      "tags": [],
      "quality": "featured",
      "source_ref": "the-private-papers-of-henry-ryecroft:william-shakespeare",
      "relations": [
        {
          "type": "related",
          "target": "johann-wolfgang-von-goethe",
          "label": "johann-wolfgang-von-goethe"
        },
        {
          "type": "related",
          "target": "literature-and-the-classics",
          "label": "literature-and-the-classics"
        },
        {
          "type": "related",
          "target": "british-museum-reading-room",
          "label": "british-museum-reading-room"
        },
        {
          "type": "related",
          "target": "henry-ryecroft",
          "label": "henry-ryecroft"
        }
      ]
    },
    {
      "id": "winter-i",
      "type": "chapter",
      "label": "Part IV: Winter — I",
      "description": "I — Part IV: Winter",
      "aliases": [
        "I"
      ],
      "tags": [],
      "quality": "unknown",
      "source_ref": "the-private-papers-of-henry-ryecroft:winter-i",
      "relations": []
    },
    {
      "id": "winter-ii",
      "type": "chapter",
      "label": "Part IV: Winter — II",
      "description": "II — Part IV: Winter",
      "aliases": [
        "II"
      ],
      "tags": [],
      "quality": "unknown",
      "source_ref": "the-private-papers-of-henry-ryecroft:winter-ii",
      "relations": []
    },
    {
      "id": "winter-iii",
      "type": "chapter",
      "label": "Part IV: Winter — III",
      "description": "III — Part IV: Winter",
      "aliases": [
        "III"
      ],
      "tags": [],
      "quality": "unknown",
      "source_ref": "the-private-papers-of-henry-ryecroft:winter-iii",
      "relations": []
    },
    {
      "id": "winter-iv",
      "type": "chapter",
      "label": "Part IV: Winter — IV",
      "description": "IV — Part IV: Winter",
      "aliases": [
        "IV"
      ],
      "tags": [],
      "quality": "unknown",
      "source_ref": "the-private-papers-of-henry-ryecroft:winter-iv",
      "relations": []
    },
    {
      "id": "winter-ix",
      "type": "chapter",
      "label": "Part IV: Winter — IX",
      "description": "IX — Part IV: Winter",
      "aliases": [
        "IX"
      ],
      "tags": [],
      "quality": "unknown",
      "source_ref": "the-private-papers-of-henry-ryecroft:winter-ix",
      "relations": []
    },
    {
      "id": "winter-v",
      "type": "chapter",
      "label": "Part IV: Winter — V",
      "description": "V — Part IV: Winter",
      "aliases": [
        "V"
      ],
      "tags": [],
      "quality": "unknown",
      "source_ref": "the-private-papers-of-henry-ryecroft:winter-v",
      "relations": []
    },
    {
      "id": "winter-vi",
      "type": "chapter",
      "label": "Part IV: Winter — VI",
      "description": "VI — Part IV: Winter",
      "aliases": [
        "VI"
      ],
      "tags": [],
      "quality": "unknown",
      "source_ref": "the-private-papers-of-henry-ryecroft:winter-vi",
      "relations": []
    },
    {
      "id": "winter-vii",
      "type": "chapter",
      "label": "Part IV: Winter — VII",
      "description": "VII — Part IV: Winter",
      "aliases": [
        "VII"
      ],
      "tags": [],
      "quality": "unknown",
      "source_ref": "the-private-papers-of-henry-ryecroft:winter-vii",
      "relations": []
    },
    {
      "id": "winter-viii",
      "type": "chapter",
      "label": "Part IV: Winter — VIII",
      "description": "VIII — Part IV: Winter",
      "aliases": [
        "VIII"
      ],
      "tags": [],
      "quality": "unknown",
      "source_ref": "the-private-papers-of-henry-ryecroft:winter-viii",
      "relations": []
    },
    {
      "id": "winter-x",
      "type": "chapter",
      "label": "Part IV: Winter — X",
      "description": "X — Part IV: Winter",
      "aliases": [
        "X"
      ],
      "tags": [],
      "quality": "unknown",
      "source_ref": "the-private-papers-of-henry-ryecroft:winter-x",
      "relations": []
    },
    {
      "id": "winter-xi",
      "type": "chapter",
      "label": "Part IV: Winter — XI",
      "description": "XI — Part IV: Winter",
      "aliases": [
        "XI"
      ],
      "tags": [],
      "quality": "unknown",
      "source_ref": "the-private-papers-of-henry-ryecroft:winter-xi",
      "relations": []
    },
    {
      "id": "winter-xii",
      "type": "chapter",
      "label": "Part IV: Winter — XII",
      "description": "XII — Part IV: Winter",
      "aliases": [
        "XII"
      ],
      "tags": [],
      "quality": "unknown",
      "source_ref": "the-private-papers-of-henry-ryecroft:winter-xii",
      "relations": []
    },
    {
      "id": "winter-xiii",
      "type": "chapter",
      "label": "Part IV: Winter — XIII",
      "description": "XIII — Part IV: Winter",
      "aliases": [
        "XIII"
      ],
      "tags": [],
      "quality": "unknown",
      "source_ref": "the-private-papers-of-henry-ryecroft:winter-xiii",
      "relations": []
    },
    {
      "id": "winter-xiv",
      "type": "chapter",
      "label": "Part IV: Winter — XIV",
      "description": "XIV — Part IV: Winter",
      "aliases": [
        "XIV"
      ],
      "tags": [],
      "quality": "unknown",
      "source_ref": "the-private-papers-of-henry-ryecroft:winter-xiv",
      "relations": []
    },
    {
      "id": "winter-xix",
      "type": "chapter",
      "label": "Part IV: Winter — XIX",
      "description": "XIX — Part IV: Winter",
      "aliases": [
        "XIX"
      ],
      "tags": [],
      "quality": "unknown",
      "source_ref": "the-private-papers-of-henry-ryecroft:winter-xix",
      "relations": []
    },
    {
      "id": "winter-xv",
      "type": "chapter",
      "label": "Part IV: Winter — XV",
      "description": "XV — Part IV: Winter",
      "aliases": [
        "XV"
      ],
      "tags": [],
      "quality": "unknown",
      "source_ref": "the-private-papers-of-henry-ryecroft:winter-xv",
      "relations": []
    },
    {
      "id": "winter-xvi",
      "type": "chapter",
      "label": "Part IV: Winter — XVI",
      "description": "XVI — Part IV: Winter",
      "aliases": [
        "XVI"
      ],
      "tags": [],
      "quality": "unknown",
      "source_ref": "the-private-papers-of-henry-ryecroft:winter-xvi",
      "relations": []
    },
    {
      "id": "winter-xvii",
      "type": "chapter",
      "label": "Part IV: Winter — XVII",
      "description": "XVII — Part IV: Winter",
      "aliases": [
        "XVII"
      ],
      "tags": [],
      "quality": "unknown",
      "source_ref": "the-private-papers-of-henry-ryecroft:winter-xvii",
      "relations": []
    },
    {
      "id": "winter-xviii",
      "type": "chapter",
      "label": "Part IV: Winter — XVIII",
      "description": "XVIII — Part IV: Winter",
      "aliases": [
        "XVIII"
      ],
      "tags": [],
      "quality": "unknown",
      "source_ref": "the-private-papers-of-henry-ryecroft:winter-xviii",
      "relations": []
    },
    {
      "id": "winter-xx",
      "type": "chapter",
      "label": "Part IV: Winter — XX",
      "description": "XX — Part IV: Winter",
      "aliases": [
        "XX"
      ],
      "tags": [],
      "quality": "unknown",
      "source_ref": "the-private-papers-of-henry-ryecroft:winter-xx",
      "relations": []
    },
    {
      "id": "winter-xxi",
      "type": "chapter",
      "label": "Part IV: Winter — XXI",
      "description": "XXI — Part IV: Winter",
      "aliases": [
        "XXI"
      ],
      "tags": [],
      "quality": "unknown",
      "source_ref": "the-private-papers-of-henry-ryecroft:winter-xxi",
      "relations": []
    },
    {
      "id": "winter-xxii",
      "type": "chapter",
      "label": "Part IV: Winter — XXII",
      "description": "XXII — Part IV: Winter",
      "aliases": [
        "XXII"
      ],
      "tags": [],
      "quality": "unknown",
      "source_ref": "the-private-papers-of-henry-ryecroft:winter-xxii",
      "relations": []
    },
    {
      "id": "winter-xxiii",
      "type": "chapter",
      "label": "Part IV: Winter — XXIII",
      "description": "XXIII — Part IV: Winter",
      "aliases": [
        "XXIII"
      ],
      "tags": [],
      "quality": "unknown",
      "source_ref": "the-private-papers-of-henry-ryecroft:winter-xxiii",
      "relations": []
    },
    {
      "id": "winter-xxiv",
      "type": "chapter",
      "label": "Part IV: Winter — XXIV",
      "description": "XXIV — Part IV: Winter",
      "aliases": [
        "XXIV"
      ],
      "tags": [],
      "quality": "unknown",
      "source_ref": "the-private-papers-of-henry-ryecroft:winter-xxiv",
      "relations": []
    },
    {
      "id": "winter-xxv",
      "type": "chapter",
      "label": "Part IV: Winter — XXV",
      "description": "XXV — Part IV: Winter",
      "aliases": [
        "XXV"
      ],
      "tags": [],
      "quality": "unknown",
      "source_ref": "the-private-papers-of-henry-ryecroft:winter-xxv",
      "relations": []
    },
    {
      "id": "winter-xxvi",
      "type": "chapter",
      "label": "Part IV: Winter — XXVI",
      "description": "XXVI — Part IV: Winter",
      "aliases": [
        "XXVI"
      ],
      "tags": [],
      "quality": "unknown",
      "source_ref": "the-private-papers-of-henry-ryecroft:winter-xxvi",
      "relations": []
    }
  ]
}